<?xml version="1.0" encoding="UTF-8"?>
<!DOCTYPE suite SYSTEM "https://testng.org/testng-1.0.dtd">
<suite  name="Suite">
<groups>
<run>
<include name="Error Validations"/>
</run>
</groups>
<listeners>
<listener class-name="E_commersetest.AbstratctCopmponents.Testnglistners" />
</listeners>
  <test thread-count="5" name="Submit order Test">
    <classes>
      <class name="Selenium_Project_01_test.SeleniuM_Framewor.Order_submit_test"/>
    </classes>
  </test> <!-- Test -->
  <test thread-count="5" name="Error Validations test">
    <classes>
      <class name="Selenium_Project_01_test.SeleniuM_Framewor.Error_validationtest"/>
      
  
    </classes>
  </test> <!-- Test -->
</suite> <!-- Suite -->
